[
  {
    "timestamp": "2025-05-27T21:41:35.532Z",
    "userPrompt": "help me start a podcast",
    "agentReply": "I will break down the user's request into UI blocks.",
    "suggestedBlocks": [
      {
        "type": "CHECKLIST",
        "title": "Podcast Setup Checklist",
        "items": [
          "Define podcast topic and format",
          "Choose recording equipment",
          "Select a podcast hosting platform",
          "Create podcast artwork",
          "Plan and record episodes",
          "Edit and finalize episodes",
          "Publish episodes and promote podcast"
        ]
      },
      {
        "type": "RESOURCE_CARD",
        "title": "Podcasting Resources",
        "items": [
          {
            "name": "Anchor",
            "purpose": "Free podcast hosting platform with creation tools",
            "recommended": "Engage with listeners through Anchor's features"
          },
          {
            "name": "Blue Yeti Microphone",
            "purpose": "Popular USB microphone for podcasting",
            "recommended": "Consider using a pop filter for better audio quality"
          },
          {
            "name": "Canva",
            "purpose": "Graphic design tool for creating podcast artwork",
            "recommended": "Use Canva's templates for quick and professional designs"
          }
        ]
      }
    ]
  },
  {
    "timestamp": "2025-05-27T21:41:35.848Z",
    "userPrompt": "help me start a podcast",
    "agentReply": "I will break down the user's request into UI blocks.",
    "suggestedBlocks": [
      {
        "type": "CHECKLIST",
        "title": "Podcast Starter Checklist",
        "items": [
          "Define podcast topic and audience",
          "Choose podcast format and length",
          "Get necessary equipment (microphone, headphones, recording software)",
          "Create podcast artwork and intro music",
          "Select a podcast hosting platform"
        ]
      },
      {
        "type": "RESOURCE_CARD",
        "title": "Podcasting Resources",
        "items": [
          {
            "name": "Anchor",
            "purpose": "All-in-one platform for recording, hosting, and distributing podcasts",
            "recommended": "Explore monetization options on Anchor"
          },
          {
            "name": "Audacity",
            "purpose": "Free audio editing software for podcast production",
            "recommended": "Join online communities for Audacity tips and tricks"
          },
          {
            "name": "Canva",
            "purpose": "Graphic design tool for creating podcast artwork",
            "recommended": "Use Canva templates for podcast cover designs"
          }
        ]
      }
    ]
  }
]